init/__init__.py
init/fine_tuning_init.py
init/model_init.py
init/peft_model_init.py
generic_fine_tuning-0.0.1.dist-info/METADATA
generic_fine_tuning-0.0.1.dist-info/WHEEL
generic_fine_tuning-0.0.1.dist-info/top_level.txt
generic_fine_tuning-0.0.1.dist-info/RECORD
